excel_to_dict/__init__.py
excel_to_dict-1.1.1.dist-info/LICENSE
excel_to_dict-1.1.1.dist-info/METADATA
excel_to_dict-1.1.1.dist-info/WHEEL
excel_to_dict-1.1.1.dist-info/top_level.txt
excel_to_dict-1.1.1.dist-info/RECORD
